chives/__init__.py
chives/__main__.py
chives/benchmark.py
chives/cli.py
chives/db.py
chives/forms.py
chives/webserver.py
chives/blueprints/__init__.py
chives/blueprints/api.py
chives/blueprints/auth.py
chives/blueprints/debug.py
chives/blueprints/exchange.py
chives/configs/__init__.py
chives/configs/default_config.py
chives/matchingengine/__init__.py
chives/matchingengine/matchingengine.py
chives/models/__init__.py
chives/models/models.py
chives/static/.DS_Store
chives/static/android-chrome-192x192.png
chives/static/android-chrome-512x512.png
chives/static/apple-touch-icon.png
chives/static/chart.js
chives/static/chartjs-adapter-moment.js
chives/static/chartjs-financial.js
chives/static/do_as_you_wish.jpeg
chives/static/favicon-16x16.png
chives/static/favicon-32x32.png
chives/static/favicon.ico
chives/static/fetchHTTP.js
chives/static/materialize.min.css
chives/static/materialize.min.js
chives/static/moment.min.js
chives/static/style.css
chives/static/fonts/noto-sans-v11-latin-regular.eot
chives/static/fonts/noto-sans-v11-latin-regular.svg
chives/static/fonts/noto-sans-v11-latin-regular.ttf
chives/static/fonts/noto-sans-v11-latin-regular.woff
chives/static/fonts/noto-sans-v11-latin-regular.woff2
chives/templates/auth/login.html
chives/templates/auth/register.html
chives/templates/exchange/base.html
chives/templates/exchange/dashboard.html
chives/templates/exchange/error.html
chives/templates/exchange/recent_orders.html
chives/templates/exchange/recent_transactions.html
chives/templates/exchange/start_company.html
chives/templates/exchange/submit_order.html
chives/templates/exchange/view_company.html
chives_exchange-0.2.3.dist-info/METADATA
chives_exchange-0.2.3.dist-info/WHEEL
chives_exchange-0.2.3.dist-info/entry_points.txt
chives_exchange-0.2.3.dist-info/top_level.txt
chives_exchange-0.2.3.dist-info/RECORD
