Metadata-Version: 2.1
Name: chives-exchange
Version: 0.2.3
Summary: Stock exchange with a matching engine and webserver
Home-page: https://github.com/xuganyu96/chives-exchange
Author: Ganyu "Bruce" Xu
Author-email: xuganyu96@gmail.com
License: UNKNOWN
Platform: UNKNOWN
Requires-Dist: Babel (==2.9.0)
Requires-Dist: cryptography (==3.2.1)
Requires-Dist: Flask (==1.1.2)
Requires-Dist: flask-login (==0.5.0)
Requires-Dist: flask-wtf (==0.14.3)
Requires-Dist: pandas (==1.1.4)
Requires-Dist: pika (==1.1.0)
Requires-Dist: pymysql (==0.10.1)
Requires-Dist: pytest (==6.1.2)
Requires-Dist: requests (==2.24.0)
Requires-Dist: SQLAlchemy (==1.3.20)
